Biblelator/Biblelator.py
Biblelator/BiblelatorGlobals.py
Biblelator/__init__.py
Biblelator/Apps/BOSManager.py
Biblelator/Apps/BiblelatorSettingsEditor.py
Biblelator/Apps/FRepEx.py
Biblelator/Apps/SwordManager.py
Biblelator/Apps/__init__.py
Biblelator/DataFiles/Biblelator.gif
Biblelator/DataFiles/Biblelator.jpg
Biblelator/DataFiles/BiblelatorLogo.gif
Biblelator/DataFiles/BiblelatorLogoSmall.gif
Biblelator/Dialogs/About.py
Biblelator/Dialogs/BiblelatorDialogs.py
Biblelator/Dialogs/BiblelatorSimpleDialogs.py
Biblelator/Dialogs/Help.py
Biblelator/Dialogs/ModalDialog.py
Biblelator/Dialogs/__init__.py
Biblelator/Helpers/AutocompleteFunctions.py
Biblelator/Helpers/AutocorrectFunctions.py
Biblelator/Helpers/BiblelatorHelpers.py
Biblelator/Helpers/SpellChecking.py
Biblelator/Helpers/__init__.py
Biblelator/Settings/BiblelatorSettingsFunctions.py
Biblelator/Settings/Settings.py
Biblelator/Settings/__init__.py
Biblelator/Windows/BibleNotesWindow.py
Biblelator/Windows/BibleReferenceCollection.py
Biblelator/Windows/BibleResourceCollection.py
Biblelator/Windows/BibleResourceWindows.py
Biblelator/Windows/ChildWindows.py
Biblelator/Windows/ESFMEditWindow.py
Biblelator/Windows/LexiconResourceWindows.py
Biblelator/Windows/TSVEditWindow.py
Biblelator/Windows/TextBoxes.py
Biblelator/Windows/TextEditWindow.py
Biblelator/Windows/USFMEditWindow.py
Biblelator/Windows/__init__.py
Biblelator-0.0.8.dist-info/LICENSE
Biblelator-0.0.8.dist-info/METADATA
Biblelator-0.0.8.dist-info/WHEEL
Biblelator-0.0.8.dist-info/entry_points.txt
Biblelator-0.0.8.dist-info/top_level.txt
Biblelator-0.0.8.dist-info/RECORD
