Metadata-Version: 2.1
Name: Biblelator
Version: 0.0.8
Summary: Biblelator — experimental USFM Bible Editor
Home-page: http://Freely-Given.org/Software/Biblelator/
Author: Robert Hunt
Author-email: Freely.Given.org+Biblelator@gmail.com
License: GPLv3
Project-URL: Source Code, https://github.com/openscriptures/Biblelator/
Keywords: Bible Scripture translation editor USFM
Platform: UNKNOWN
Classifier: Development Status :: 2 - Pre-Alpha
Classifier: Intended Audience :: Developers
Classifier: Intended Audience :: Religion
Classifier: Topic :: Religion
Classifier: License :: OSI Approved :: GNU General Public License v3 (GPLv3)
Classifier: Programming Language :: Python :: 3.7
Classifier: Programming Language :: Python :: 3.8
Classifier: Operating System :: OS Independent
Requires-Python: >=3.7
Requires-Dist: BibleOrgSys (>=0.0.20)
